dataxmissionprotocol/__init__.py
dataxmissionprotocol/field.py
dataxmissionprotocol/packet.py
dataxmissionprotocol/packet55v1.py
dataxmissionprotocol/parser.py
dataxmissionprotocol/version.py
dataxmissionprotocol/formats/__init__.py
dataxmissionprotocol/formats/baseformat.py
dataxmissionprotocol/formats/simpleformat.py
dataxmissionprotocol/formats/zx55v1.py
dataxmissionprotocol/formats/zx55v2.py
dataxmissionprotocol/ports/__init__.py
dataxmissionprotocol/ports/connectionlistener.py
dataxmissionprotocol/ports/port.py
dataxmissionprotocol/ports/queue/__init__.py
dataxmissionprotocol/ports/queue/connectionestablished.py
dataxmissionprotocol/ports/queue/connectionlost.py
dataxmissionprotocol/ports/queue/datareceived.py
dataxmissionprotocol/ports/queue/processerror.py
dataxmissionprotocol/ports/serial/__init__.py
dataxmissionprotocol/ports/serial/protocol.py
dataxmissionprotocol/ports/serial/readerthread.py
dataxmissionprotocol/ports/serial/serial.py
dataxmissionprotocol-2.3.1.dist-info/LICENSE
dataxmissionprotocol-2.3.1.dist-info/METADATA
dataxmissionprotocol-2.3.1.dist-info/WHEEL
dataxmissionprotocol-2.3.1.dist-info/top_level.txt
dataxmissionprotocol-2.3.1.dist-info/RECORD
