Metadata-Version: 2.1
Name: dataxmissionprotocol
Version: 2.3.1
Summary: Data transmission protocol package
Home-page: https://github.com/RobinBobin/data-transmission-protocol
Author: Ruben Shalimov
Author-email: r_shalimov@inbox.ru
License: UNKNOWN
Platform: UNKNOWN
Classifier: Programming Language :: Python :: 3
Classifier: Operating System :: OS Independent
Requires-Dist: simple-common-utils
